dns_query/__init__.py
dns_query/__main__.py
dns_query/server.py
dns_query-0.1.1.dist-info/METADATA
dns_query-0.1.1.dist-info/WHEEL
dns_query-0.1.1.dist-info/entry_points.txt
dns_query-0.1.1.dist-info/licenses/LICENSE
dns_query-0.1.1.dist-info/RECORD
