Metadata-Version: 2.4
Name: dns-query
Version: 0.1.1
Summary: A simple DNS query server exposing a website fetching tool
Author: huiqinzhang
Maintainer-email: huiqinzhang <374228265@qq.com>
License: MIT
License-File: LICENSE
Keywords: automation,dns,fetch,query,web
Classifier: Development Status :: 4 - Beta
Classifier: Intended Audience :: Developers
Classifier: License :: OSI Approved :: MIT License
Classifier: Programming Language :: Python :: 3
Classifier: Programming Language :: Python :: 3.10
Requires-Python: >=3.10
Requires-Dist: anyio>=4.5
Requires-Dist: click>=8.1.0
Requires-Dist: dnspython>=2.7.0
Requires-Dist: httpx>=0.27
Requires-Dist: mcp
Requires-Dist: starlette>=0.46.2
